Metadata-Version: 2.1
Name: pybunny
Version: 0.0.1
Summary: UNKNOWN
Home-page: https://github.com/sulstice/Bunny
Author: Suliman Sharif
Author-email: sharifsuliman1@gmail.com
License: MIT
Keywords: bunny ssh jupyter notebook
Platform: UNKNOWN
Classifier: Development Status :: 4 - Beta
Classifier: Natural Language :: English
Classifier: License :: OSI Approved :: MIT License
Classifier: Intended Audience :: Developers
Classifier: Programming Language :: Python :: 3
Classifier: Programming Language :: Python :: 3.3
Classifier: Programming Language :: Python :: 3.4
Classifier: Programming Language :: Python :: 3.5
Classifier: Programming Language :: Python :: 3.6
Classifier: Programming Language :: Python :: 3.7
